five/intid/README.rst
five/intid/__init__.py
five/intid/base.zcml
five/intid/cmfdirectoryview.zcml
five/intid/configure.zcml
five/intid/install.pt
five/intid/intid.py
five/intid/keyreference.py
five/intid/lsm.py
five/intid/registrations.pt
five/intid/site.py
five/intid/subscriber.zcml
five/intid/test.zcml
five/intid/tests.py
five/intid/unreferenceable.py
five/intid/utils.py
five_intid-3.0.2.dist-info/METADATA
five_intid-3.0.2.dist-info/WHEEL
five_intid-3.0.2.dist-info/top_level.txt
five_intid-3.0.2.dist-info/RECORD
