Metadata-Version: 2.2
Name: five.intid
Version: 3.0.2
Summary: Zope support for zope.intid
Home-page: https://github.com/plone/five.intid
Author: Whit Morris
Author-email: whit@openplans.org
License: ZPL
Keywords: 'zope2 intid'
Classifier: Development Status :: 5 - Production/Stable
Classifier: Framework :: Plone
Classifier: Framework :: Plone :: 6.0
Classifier: Framework :: Plone :: Core
Classifier: Framework :: Zope :: 5
Classifier: License :: OSI Approved :: Zope Public License
Classifier: Programming Language :: Python
Classifier: Programming Language :: Python :: 3.8
Classifier: Programming Language :: Python :: 3.9
Classifier: Programming Language :: Python :: 3.10
Classifier: Programming Language :: Python :: 3.11
Requires-Python: >=3.8
Requires-Dist: AccessControl
Requires-Dist: Acquisition>=4.0.1
Requires-Dist: Products.CMFCore
Requires-Dist: ZODB
Requires-Dist: Zope
Requires-Dist: five.localsitemanager
Requires-Dist: persistent
Requires-Dist: setuptools
Requires-Dist: zope.intid
Requires-Dist: zope.component
Requires-Dist: zope.event
Requires-Dist: zope.interface
Requires-Dist: zope.lifecycleevent
Requires-Dist: zope.keyreference
Requires-Dist: zope.location
Dynamic: author
Dynamic: author-email
Dynamic: classifier
Dynamic: description
Dynamic: description-content-type
Dynamic: home-page
Dynamic: keywords
Dynamic: license
Dynamic: requires-dist
Dynamic: requires-python
Dynamic: summary
